distancefrompicture/CameraProperties.py
distancefrompicture/DistanceFinder.py
distancefrompicture/TargetProperties.py
distancefrompicture/__init__.py
distancefrompicture-1.0.0b1.dist-info/DESCRIPTION.rst
distancefrompicture-1.0.0b1.dist-info/METADATA
distancefrompicture-1.0.0b1.dist-info/RECORD
distancefrompicture-1.0.0b1.dist-info/WHEEL
distancefrompicture-1.0.0b1.dist-info/metadata.json
distancefrompicture-1.0.0b1.dist-info/top_level.txt
