Metadata-Version: 2.0
Name: distancefrompicture
Version: 1.0.0b1
Summary: A small python module for determining the location of objects within         static images based on characterstics of the object and the camera
Home-page: https://www.github.com/Robtom5/        distance_from_picture/blob/master/README.md
Author: Robert Thomas
Author-email: robtom_5@mac.com
License: MIT
Platform: UNKNOWN
Classifier: Development Status :: 3 - Alpha
Classifier: License :: OSI Approved :: MIT License
Classifier: Programming Language :: Python :: 3.4
Requires-Python: >=3
Requires-Dist: numpy
